ezcad_plugins/__init__.py
ezcad_plugins/cube.py
ezcad_plugins/cube.yapsy-plugin
ezcad_plugins/cube_menubar.py
ezcad_plugins/cube_menubar.yapsy-plugin
ezcad_plugins/gsurf.py
ezcad_plugins/gsurf.yapsy-plugin
ezcad_plugins/gsurf_menubar.py
ezcad_plugins/gsurf_menubar.yapsy-plugin
ezcad_plugins/label.py
ezcad_plugins/label.yapsy-plugin
ezcad_plugins/label_menubar.py
ezcad_plugins/label_menubar.yapsy-plugin
ezcad_plugins/line.py
ezcad_plugins/line.yapsy-plugin
ezcad_plugins/line_menubar.py
ezcad_plugins/line_menubar.yapsy-plugin
ezcad_plugins/point.py
ezcad_plugins/point.yapsy-plugin
ezcad_plugins/point_menubar.py
ezcad_plugins/point_menubar.yapsy-plugin
ezcad_plugins/polygon.py
ezcad_plugins/polygon.yapsy-plugin
ezcad_plugins/polygon_menubar.py
ezcad_plugins/polygon_menubar.yapsy-plugin
ezcad_plugins/survey.py
ezcad_plugins/survey.yapsy-plugin
ezcad_plugins/survey_menubar.py
ezcad_plugins/survey_menubar.yapsy-plugin
ezcad_plugins/tsurf.py
ezcad_plugins/tsurf.yapsy-plugin
ezcad_plugins/tsurf_menubar.py
ezcad_plugins/tsurf_menubar.yapsy-plugin
ezcad_plugins/gocube/__init__.py
ezcad_plugins/gocube/bartender.cp37-win_amd64.exp
ezcad_plugins/gocube/bartender.cp37-win_amd64.lib
ezcad_plugins/gocube/bartender.cp37-win_amd64.pyd
ezcad_plugins/gocube/cube.cp37-win_amd64.exp
ezcad_plugins/gocube/cube.cp37-win_amd64.lib
ezcad_plugins/gocube/cube.cp37-win_amd64.pyd
ezcad_plugins/gocube/cut.py
ezcad_plugins/gocube/cut_dialog.py
ezcad_plugins/gocube/dbsqlite.py
ezcad_plugins/gocube/deprecated.py
ezcad_plugins/gocube/face_change.py
ezcad_plugins/gocube/function.py
ezcad_plugins/gocube/info_table.py
ezcad_plugins/gocube/resample.py
ezcad_plugins/gocube/section_image3d.cp37-win_amd64.exp
ezcad_plugins/gocube/section_image3d.cp37-win_amd64.lib
ezcad_plugins/gocube/section_image3d.cp37-win_amd64.pyd
ezcad_plugins/gocube/section_plane.cp37-win_amd64.exp
ezcad_plugins/gocube/section_plane.cp37-win_amd64.lib
ezcad_plugins/gocube/section_plane.cp37-win_amd64.pyd
ezcad_plugins-0.2.4.dist-info/METADATA
ezcad_plugins-0.2.4.dist-info/WHEEL
ezcad_plugins-0.2.4.dist-info/top_level.txt
ezcad_plugins-0.2.4.dist-info/RECORD
